tests/__init__.py
tests/test_manipulação_de_arquivos.py
tests/test_misc.py
tests/test_web_scrapping.py
toolboxy/__init__.py
toolboxy/error_identification.py
toolboxy/file_manipulation.py
toolboxy/free_APIs.py
toolboxy/git_tools.py
toolboxy/misc.py
toolboxy/optimization.py
toolboxy/web_scrapping.py
toolboxy/windows_tools.py
toolboxy-0.1.2.dist-info/LICENSE
toolboxy-0.1.2.dist-info/METADATA
toolboxy-0.1.2.dist-info/WHEEL
toolboxy-0.1.2.dist-info/top_level.txt
toolboxy-0.1.2.dist-info/RECORD
