Metadata-Version: 2.1
Name: toolboxy
Version: 0.1.2
Summary: This repository is a collection of tools for developers to easily access relevant solutions for development in order to accelerate their workflow. It provides a variety of resources that are constantly used.
Home-page: https://github.com/Lima-e-Silva/toolboxy
Author: Lima & Silva
Author-email: luizpaulo@protonmail.com
Keywords: python,tools,programming,devs
Classifier: Development Status :: 3 - Alpha
Classifier: Intended Audience :: Developers
Classifier: Topic :: Software Development :: Libraries
Classifier: Topic :: Software Development :: Libraries :: Python Modules
Classifier: Programming Language :: Python :: 3.6
Classifier: Programming Language :: Python :: 3.7
Classifier: Programming Language :: Python :: 3.8
Classifier: Programming Language :: Python :: 3.9
Classifier: Programming Language :: Python :: 3.10
Classifier: Operating System :: Microsoft :: Windows
License-File: LICENSE
Requires-Dist: beautifulsoup4
Requires-Dist: loguru
Requires-Dist: openai
Requires-Dist: pipreqs
Requires-Dist: pyperclip
Requires-Dist: python-dotenv
Requires-Dist: requests
Requires-Dist: setuptools
Requires-Dist: snakeviz
Requires-Dist: winotify
